bsdd_json/BsddClass.py
bsdd_json/BsddClassProperty.py
bsdd_json/BsddDictionary.py
bsdd_json/BsddProperty.py
bsdd_json/BsddPropertyRelation.py
bsdd_json/__init__.py
bsdd_json/models.py
bsdd_json/type_hints.py
bsdd_json/utils/__init__.py
bsdd_json/utils/class_utils.py
bsdd_json/utils/dictionary_utils.py
bsdd_json/utils/property_utils.py
bsdd_json-0.1.2.dist-info/METADATA
bsdd_json-0.1.2.dist-info/WHEEL
bsdd_json-0.1.2.dist-info/top_level.txt
bsdd_json-0.1.2.dist-info/RECORD
