Metadata-Version: 2.4
Name: bsdd_json
Version: 0.1.2
Summary: bSDD JSON data models and utilities
Author: Christoph Mellüh
License: MIT
Requires-Python: >=3.10
Requires-Dist: pydantic>=2.7
Requires-Dist: bsdd
